data_iq/__init__.py
data_iq/dataiq_class.py
src/__init__.py
src/models/__init__.py
src/models/cnn_models.py
src/models/neuralnets.py
src/models/nlp_models.py
src/utils/__init__.py
src/utils/data_loader.py
src/utils/exp3_helpers.py
src/utils/group_dro_helpers.py
src/utils/utils.py
data_iq-0.0.1.dist-info/LICENSE
data_iq-0.0.1.dist-info/METADATA
data_iq-0.0.1.dist-info/WHEEL
data_iq-0.0.1.dist-info/top_level.txt
data_iq-0.0.1.dist-info/RECORD
