Metadata-Version: 2.1
Name: data-iq
Version: 0.0.1
Summary: Data-IQ: Characterizing subgroups with heterogeneous outcomes in tabular data
Home-page: https://arxiv.org/abs/2202.08836
Author: Nabeel Seedat
License: MIT
Keywords: data-centric AI,data quality,uncertainty
Classifier: License :: OSI Approved :: MIT License
Classifier: Operating System :: OS Independent
Classifier: Programming Language :: Python :: 3
Classifier: Topic :: Scientific/Engineering :: Artificial Intelligence
License-File: LICENSE
Requires-Dist: autograd-lib
Requires-Dist: numpy
Requires-Dist: torch (>=1.9.1)
Requires-Dist: torchvision (>=0.11.1)
Requires-Dist: importlib-metadata ; python_version < "3.8"
Provides-Extra: testing
Requires-Dist: SciencePlots ; extra == 'testing'
Requires-Dist: aum ; extra == 'testing'
Requires-Dist: autograd-lib ; extra == 'testing'
Requires-Dist: bandit ; extra == 'testing'
Requires-Dist: catboost (>=1.1) ; extra == 'testing'
Requires-Dist: click ; extra == 'testing'
Requires-Dist: flake8 ; extra == 'testing'
Requires-Dist: ipykernel ; extra == 'testing'
Requires-Dist: isort ; extra == 'testing'
Requires-Dist: lightgbm ; extra == 'testing'
Requires-Dist: matplotlib ; extra == 'testing'
Requires-Dist: nbconvert ; extra == 'testing'
Requires-Dist: nltk ; extra == 'testing'
Requires-Dist: notebook ; extra == 'testing'
Requires-Dist: numpy ; extra == 'testing'
Requires-Dist: pandas (>=1.3.5) ; extra == 'testing'
Requires-Dist: pre-commit ; extra == 'testing'
Requires-Dist: protobuf (>=4.21.8) ; extra == 'testing'
Requires-Dist: py ; extra == 'testing'
Requires-Dist: pytest ; extra == 'testing'
Requires-Dist: pytest-benchmark ; extra == 'testing'
Requires-Dist: pytest-cov ; extra == 'testing'
Requires-Dist: pytest-xdist[psutil] ; extra == 'testing'
Requires-Dist: pytest-xprocess ; extra == 'testing'
Requires-Dist: scikit-learn (>=1.0.2) ; extra == 'testing'
Requires-Dist: scipy (>=1.7.3) ; extra == 'testing'
Requires-Dist: sdv ; extra == 'testing'
Requires-Dist: seaborn ; extra == 'testing'
Requires-Dist: tqdm ; extra == 'testing'
Requires-Dist: umap-learn ; extra == 'testing'
Requires-Dist: uq360 ; extra == 'testing'
Requires-Dist: xgboost (>=1.6.2) ; extra == 'testing'
Requires-Dist: xlrd ; extra == 'testing'
